gogoanime/__init__.py
gogoanime-1.0.0.dist-info/METADATA
gogoanime-1.0.0.dist-info/WHEEL
gogoanime-1.0.0.dist-info/top_level.txt
gogoanime-1.0.0.dist-info/RECORD
