Metadata-Version: 2.1
Name: gogoanime
Version: 1.0.0
Summary: Unofficial python wrapper for Gogoanime API
Home-page: https://github.com/otakatsu/gogoanimepy.git
Author: otakatsu
Author-email: moezilla@otakatsu.studio
License: License :: OSI Approved :: GNU Lesser General Public License v3 (LGPLv3)
Classifier: Programming Language :: Python :: 3
Classifier: Programming Language :: Python :: 3.6
Classifier: Programming Language :: Python :: 3.7
Classifier: Programming Language :: Python :: 3.8
Classifier: Programming Language :: Python :: 3.9
Classifier: Operating System :: OS Independent
Requires-Python: >=3.6
Requires-Dist: bs4
Requires-Dist: requests
Requires-Dist: requests-html
